{
  "project_info": {
    "project_number": "826887945639",
    "firebase_url": "https://brenda-wallet.firebaseio.com",
    "project_id": "brenda-wallet",
    "storage_bucket": "brenda-wallet.appspot.com"
  },
  "client": [
    {
      "client_info": {
        "mobilesdk_app_id": "1:826887945639:android:e530a2ebef921ad4274a82",
        "android_client_info": {
          "package_name": "com.brendarewards"
        }
      },
      "oauth_client": [
        {
          "client_id": "826887945639-ijgmb46003ot20ikggi2dt6d4dg3pr64.apps.googleusercontent.com",
          "client_type": 3
        }
      ],
      "api_key": [
        {
          "current_key": "AIzaSyDJeLsIehfD55XQBuuP8f9mz9MUNs04NBQ"
        }
      ],
      "services": {
        "appinvite_service": {
          "other_platform_oauth_client": [
            {
              "client_id": "826887945639-ijgmb46003ot20ikggi2dt6d4dg3pr64.apps.googleusercontent.com",
              "client_type": 3
            }
          ]
        }
      }
    },
    {
      "client_info": {
        "mobilesdk_app_id": "1:826887945639:android:8702222b61c321b3274a82",
        "android_client_info": {
          "package_name": "com.materialx.materialx_flutter"
        }
      },
      "oauth_client": [
        {
          "client_id": "826887945639-ijgmb46003ot20ikggi2dt6d4dg3pr64.apps.googleusercontent.com",
          "client_type": 3
        }
      ],
      "api_key": [
        {
          "current_key": "AIzaSyDJeLsIehfD55XQBuuP8f9mz9MUNs04NBQ"
        }
      ],
      "services": {
        "appinvite_service": {
          "other_platform_oauth_client": [
            {
              "client_id": "826887945639-ijgmb46003ot20ikggi2dt6d4dg3pr64.apps.googleusercontent.com",
              "client_type": 3
            }
          ]
        }
      }
    }
  ],
  "configuration_version": "1"
}